mock.py
mcok-0.0.2.dist-info/DESCRIPTION.rst
mcok-0.0.2.dist-info/METADATA
mcok-0.0.2.dist-info/RECORD
mcok-0.0.2.dist-info/WHEEL
mcok-0.0.2.dist-info/metadata.json
mcok-0.0.2.dist-info/top_level.txt
mcok-0.0.2.dist-info/zip-safe
