Metadata-Version: 2.0
Name: mcok
Version: 0.0.2
Summary: Mock mock's Mock
Home-page: https://github.com/pylola/mcok
Author: Michał Jaworski
Author-email: swistakm@gmail.com
License: BSD
Platform: UNKNOWN
Classifier: Development Status :: 4 - Beta
Classifier: Intended Audience :: Developers
Classifier: License :: OSI Approved :: BSD License
Classifier: Operating System :: OS Independent
Classifier: Programming Language :: Python
